dualmesh/__init__.py
dualmesh/dualmesh.py
dualmesh-0.13.3.dist-info/LICENSE
dualmesh-0.13.3.dist-info/METADATA
dualmesh-0.13.3.dist-info/WHEEL
dualmesh-0.13.3.dist-info/top_level.txt
dualmesh-0.13.3.dist-info/RECORD
