Metadata-Version: 2.1
Name: dualmesh
Version: 0.13.3
Summary: Python module for generating dual meshes
Home-page: https://github.com/BartoszBartmanski/DualMesh
Author: Bartosz Bartmanski
Author-email: bartoszbartmanski@gmail.com
License: UNKNOWN
Platform: UNKNOWN
Requires-Python: >=3.6
Requires-Dist: meshio
Requires-Dist: numpy
